flask_tools/__init__.py
flask_tools/configparser.py
flask_tools/serialise.py
flask_decorator_tools-0.0.8.dist-info/LICENSE
flask_decorator_tools-0.0.8.dist-info/METADATA
flask_decorator_tools-0.0.8.dist-info/WHEEL
flask_decorator_tools-0.0.8.dist-info/top_level.txt
flask_decorator_tools-0.0.8.dist-info/RECORD
