Metadata-Version: 2.1
Name: flask-decorator-tools
Version: 0.0.8
Summary: A package with tools for use with flask
Home-page: https://github.com/max-wickham/flask_tools
Author: Max Wickham
Author-email: maxwickhammonro@gmail.com
License: UNKNOWN
Platform: UNKNOWN
Classifier: Programming Language :: Python :: 3
Classifier: License :: OSI Approved :: MIT License
Classifier: Operating System :: OS Independent
Requires-Python: >=3.6
License-File: LICENSE
